adpac_auth/__init__.py
adpac_auth/module1.py
adpac_auth-0.0.1.dist-info/METADATA
adpac_auth-0.0.1.dist-info/WHEEL
adpac_auth-0.0.1.dist-info/top_level.txt
adpac_auth-0.0.1.dist-info/RECORD
